newconan/newconan.py
newconan/data/.clang-format
newconan/data/.gitlab-ci.yml
newconan/data/.travis.yml
newconan/data/CMakeSettings.json
newconan/data/README.md
newconan/data/appveyor.yml
newconan/data/build.py
newconan/data/conan.cmake
newconan/data/conanfile.py
newconan/data/export.yml
newconan/data/gitignore
newconan/data/main.cpp
newconan/data/main.h
newconan/data/mainlibrary.cpp
newconan/data/symlink.cmake
newconan/data/symlink.py
newconan/data/test.cpp
newconan/data/testLibrary.cpp
newconan/data/.travis/install.sh
newconan/data/.travis/run.sh
newconan-2.6.dist-info/METADATA
newconan-2.6.dist-info/WHEEL
newconan-2.6.dist-info/entry_points.txt
newconan-2.6.dist-info/top_level.txt
newconan-2.6.dist-info/RECORD
