Metadata-Version: 2.1
Name: newconan
Version: 2.6
Summary: New cmake project based on conan
Home-page: https://github.com/wumo-util/newconan
Author: wumo
License: MIT
Platform: UNKNOWN
Requires-Python: >=3.6
Requires-Dist: conan
